BorgTestGenerator/__init__.py
BorgTestGenerator/assistant.py
BorgTestGenerator/agents/__init__.py
BorgTestGenerator/agents/base_agent.py
BorgTestGenerator/agents/base_agent_writer.py
BorgTestGenerator/agents/unittestwriter.py
BorgTestGenerator/agents/swarm/__init__.py
BorgTestGenerator/agents/swarm/docs_swarm/__init__.py
BorgTestGenerator/agents/swarm/docs_swarm/agent_analyste_de_code.py
BorgTestGenerator/agents/swarm/docs_swarm/agent_chef_de_documentation.py
BorgTestGenerator/agents/swarm/docs_swarm/agent_de_mise_en_page.py
BorgTestGenerator/agents/swarm/docs_swarm/agent_de_traduction.py
BorgTestGenerator/agents/swarm/docs_swarm/agent_redacteur_technique.py
BorgTestGenerator/agents/swarm/docs_swarm/agent_verificateur_de_documentation.py
BorgTestGenerator/agents/swarm/docs_swarm/base_swarm_agent.py
BorgTestGenerator/parsers/__init__.py
BorgTestGenerator/parsers/code_blocks_parsing.py
BorgTestGenerator/utils/__init__.py
BorgTestGenerator/utils/files.py
tests/__init__.py
tests/test_assistant.py
tests/test_base_agent.py
tests/test_base_agent_writer.py
tests/test_code_blocks_parsing.py
tests/test_files.py
tests/test_unittestwriter.py
BorgTestGenerator-0.3.10.dist-info/LICENSE
BorgTestGenerator-0.3.10.dist-info/METADATA
BorgTestGenerator-0.3.10.dist-info/WHEEL
BorgTestGenerator-0.3.10.dist-info/top_level.txt
BorgTestGenerator-0.3.10.dist-info/RECORD
